ocdsmerge_rs/__init__.py
ocdsmerge_rs/exceptions.py
ocdsmerge_rs/ocdsmerge_rs.cpython-314-x86_64-linux-gnu.so
ocdsmerge_rs-0.1.3.dist-info/METADATA
ocdsmerge_rs-0.1.3.dist-info/WHEEL
ocdsmerge_rs-0.1.3.dist-info/licenses/LICENSE
ocdsmerge_rs-0.1.3.dist-info/RECORD
